pipen_verbose.py
pipen_verbose-1.1.0.dist-info/METADATA
pipen_verbose-1.1.0.dist-info/WHEEL
pipen_verbose-1.1.0.dist-info/entry_points.txt
pipen_verbose-1.1.0.dist-info/RECORD
